{
  "slug": "australian-shepherd-cost",
  "breed": "Australian Shepherd",
  "species": "dog",
  "localPath": "assets/images/breeds/australian-shepherd-cost/hero.jpg",
  "sourceWebsite": "Wikimedia Commons",
  "sourcePage": "https://commons.wikimedia.org/wiki/File:Wet_Australian_Shepherd_dog%2C_side_view.jpg",
  "sourceFileTitle": "File:Wet Australian Shepherd dog, side view.jpg",
  "downloadUrl": "https://upload.wikimedia.org/wikipedia/commons/thumb/2/28/Wet_Australian_Shepherd_dog%2C_side_view.jpg/1280px-Wet_Australian_Shepherd_dog%2C_side_view.jpg?utm_source=commons.wikimedia.org&utm_campaign=imageinfo&utm_content=thumbnail",
  "mime": "image/jpeg",
  "width": 1280,
  "height": 853,
  "bytes": 508916,
  "license": "CC0",
  "licenseUrl": "http://creativecommons.org/publicdomain/zero/1.0/deed.en",
  "attributionRequired": false,
  "artist": "Joselodos",
  "credit": "Own work",
  "imageDescription": "Wet Australian Shepherd dog, side view",
  "selectedScore": 57,
  "altSuggestion": "Australian Shepherd dog",
  "reviewNote": "Free-license image from Wikimedia Commons. Verify visual breed accuracy before publishing."
}