{
  "slug": "maine-coon-cat-cost",
  "breed": "Maine Coon cat",
  "species": "cat",
  "localPath": "assets/images/breeds/maine-coon-cat-cost/hero.jpg",
  "sourceWebsite": "Wikimedia Commons",
  "sourcePage": "https://commons.wikimedia.org/wiki/File:Maine_Coon_Cat_Atticus.jpg",
  "sourceFileTitle": "File:Maine Coon Cat Atticus.jpg",
  "downloadUrl": "https://upload.wikimedia.org/wikipedia/commons/thumb/5/58/Maine_Coon_Cat_Atticus.jpg/1280px-Maine_Coon_Cat_Atticus.jpg?utm_source=commons.wikimedia.org&utm_campaign=imageinfo&utm_content=thumbnail",
  "mime": "image/jpeg",
  "width": 1280,
  "height": 960,
  "bytes": 233680,
  "license": "Public domain",
  "licenseUrl": "",
  "attributionRequired": false,
  "artist": "Hollakr",
  "credit": "Own work",
  "imageDescription": "Maine Coons can grow to be quite large. This MC is about a year old, and about 3/4 grown.",
  "selectedScore": 57,
  "altSuggestion": "Maine Coon cat cat",
  "reviewNote": "Free-license image from Wikimedia Commons. Verify visual breed accuracy before publishing."
}